pypkggen/__init__.py
pypkggen/files.py
pypkggen/licenses.py
pypkggen/pypkggen.py
pypkggen/setup_file.py
pypkggen-0.0.1.dist-info/LICENSE
pypkggen-0.0.1.dist-info/METADATA
pypkggen-0.0.1.dist-info/WHEEL
pypkggen-0.0.1.dist-info/top_level.txt
pypkggen-0.0.1.dist-info/RECORD
