Metadata-Version: 2.1
Name: pypkggen
Version: 0.0.1
Summary: A Python library for creating packages in a fast and easy way.
Home-page: https://github.com/Samuel-HSSP/pypkggen
Author: Samuel Ogunleke
Author-email: samuelayomidehssp@gmail.com
License: UNKNOWN
Project-URL: Bug Tracker, https://github.com/Samuel-HSSP/pypkggen/issues
Platform: UNKNOWN
Classifier: Programming Language :: Python :: 3
Classifier: License :: OSI Approved :: MIT License
Classifier: Operating System :: OS Independent
Requires-Python: >=3.6
License-File: LICENSE
Requires-Dist: build ; python_version >= "0.7.0"
Requires-Dist: twine ; python_version >= "3.8.0"
